LICENSE
setup.py
django_oncall_rota.egg-info/PKG-INFO
django_oncall_rota.egg-info/SOURCES.txt
django_oncall_rota.egg-info/dependency_links.txt
django_oncall_rota.egg-info/requires.txt
django_oncall_rota.egg-info/top_level.txt
engineering/__init__.py
engineering/admin.py
engineering/apps.py
engineering/models.py
engineering/tests.py
engineering/views.py
engineering/migrations/0001_initial.py
engineering/migrations/__init__.py
laboratory/__init__.py
laboratory/admin.py
laboratory/apps.py
laboratory/models.py
laboratory/tests.py
laboratory/views.py
laboratory/migrations/0001_initial.py
laboratory/migrations/0002_sitelocation.py
laboratory/migrations/0003_dateactive_deskphone.py
laboratory/migrations/0004_auto_20191210_1232.py
laboratory/migrations/0005_remove_dateactive_deskphone.py
laboratory/migrations/0006_dateactive_deskphone.py
laboratory/migrations/__init__.py
oncall/__init__.py
oncall/settings.py
oncall/urls.py
oncall/wsgi.py
rota/__init__.py
rota/admin.py
rota/api.py
rota/apps.py
rota/filters.py
rota/models.py
rota/tests.py
rota/urls.py
rota/views.py
rota/migrations/0001_initial.py
rota/migrations/0002_auto_20191015_1149.py
rota/migrations/0003_auto_20191015_1446.py
rota/migrations/0004_auto_20191015_1506.py
rota/migrations/__init__.py
spm/__init__.py
spm/admin.py
spm/apps.py
spm/models.py
spm/tests.py
spm/urls.py
spm/views.py
spm/migrations/0001_initial.py
spm/migrations/__init__.py